pallapay/__init__.py
pallapay/enums.py
pallapay/payment.py
pallapay/request.py
pallapay/schema.py
pallapay/utils.py
python_pallapay-1.0.0.dist-info/LICENSE
python_pallapay-1.0.0.dist-info/METADATA
python_pallapay-1.0.0.dist-info/WHEEL
python_pallapay-1.0.0.dist-info/top_level.txt
python_pallapay-1.0.0.dist-info/RECORD
