Metadata-Version: 2.1
Name: python-pallapay
Version: 1.0.0
Summary: Pallapay Python SDK to accept crypto currency payments.
Home-page: https://github.com/pallapay/python-pallapay
Author: Pallapay Development Team
Author-email: development@pallapay.com
License: MIT
Project-URL: Bug Tracker, https://github.com/pallapay/python-pallapay/issues
Project-URL: Documentation, https://www.pallapay.com/developers
Project-URL: repository, https://github.com/pallapay/python-pallapay
Keywords: pallapay bitcoin crypto payment gateway client
Classifier: Intended Audience :: Developers
Classifier: License :: OSI Approved :: MIT License
Classifier: Operating System :: OS Independent
Classifier: Programming Language :: Python :: 3
Classifier: Programming Language :: Python :: 3.5
Classifier: Programming Language :: Python :: 3.6
Classifier: Programming Language :: Python :: 3.7
Classifier: Programming Language :: Python
Classifier: Topic :: Software Development :: Libraries :: Python Modules
Requires-Python: >=3.6
License-File: LICENSE
Requires-Dist: requests (==2.28.1)
Requires-Dist: pydantic (==1.9.2)
